browserforge/bayesian_network.py
browserforge/datapoints/__init__.py
browserforge/datapoints/data/browser-helper-file.json
browserforge/datapoints/data/fingerprint-network.zip
browserforge/datapoints/data/header-network.zip
browserforge/datapoints/data/headers-order.json
browserforge/datapoints/data/input-network.zip
browserforge/download.py
browserforge/fingerprints/__init__.py
browserforge/fingerprints/generator.py
browserforge/headers/__init__.py
browserforge/headers/generator.py
browserforge/headers/utils.py
browserforge/injectors/__init__.py
browserforge/injectors/data/__init__.py
browserforge/injectors/data/utils.js.xz
browserforge/injectors/playwright/__init__.py
browserforge/injectors/playwright/injector.py
browserforge/injectors/pyppeteer/__init__.py
browserforge/injectors/pyppeteer/injector.py
browserforge/injectors/undetected_playwright/__init__.py
browserforge/injectors/undetected_playwright/injector.py
browserforge/injectors/utils.py
browserforge/py.typed
browserforge_local-1.2.4.dist-info/METADATA
browserforge_local-1.2.4.dist-info/WHEEL
browserforge_local-1.2.4.dist-info/licenses/LICENSE
browserforge_local-1.2.4.dist-info/licenses/NOTICE
browserforge_local-1.2.4.dist-info/RECORD
