Metadata-Version: 2.4
Name: browserforge-local
Version: 1.2.4
Summary: Intelligent browser header & fingerprint generator
License: Apache-2.0
License-File: LICENSE
License-File: NOTICE
Keywords: client,headers,fingerprint,generator,browser,http,scraping,requests,playwright
Author: daijro
Author-email: daijro.dev@gmail.com
Requires-Python: >=3.8,<4.0
Classifier: License :: OSI Approved :: Apache Software License
Classifier: Programming Language :: Python :: 3
Classifier: Programming Language :: Python :: 3.8
Classifier: Programming Language :: Python :: 3.9
Classifier: Programming Language :: Python :: 3.10
Classifier: Programming Language :: Python :: 3.11
Classifier: Programming Language :: Python :: 3.12
Classifier: Programming Language :: Python :: 3.13
Classifier: Programming Language :: Python :: 3.14
Classifier: Topic :: Internet :: WWW/HTTP
Classifier: Topic :: Internet :: WWW/HTTP :: Browsers
Classifier: Topic :: Software Development :: Libraries :: Python Modules
Provides-Extra: all
Requires-Dist: apify_fingerprint_datapoints
Requires-Dist: click
Requires-Dist: orjson ; extra == "all"
Requires-Dist: typing_extensions ; python_version < "3.10"
Project-URL: Repository, https://github.com/bingal/browserforge-local
